{
  "best": {
    "shrink": 0.4,
    "wlin": 0.7,
    "sint": 3.0,
    "sslo": 0.01,
    "avg_acc": 0.9721,
    "avg_brier": 0.1048,
    "per_year_acc": {
      "2010": 1.0,
      "2016": 0.85,
      "2018": 0.9857,
      "2020": 1.0,
      "2022": 1.0,
      "2024": 0.8971
    },
    "per_year_brier": {
      "2010": 0.1015,
      "2016": 0.0846,
      "2018": 0.1843,
      "2020": 0.0171,
      "2022": 0.0848,
      "2024": 0.1073
    },
    "per_year_n": {
      "2010": 86,
      "2016": 20,
      "2018": 70,
      "2020": 30,
      "2022": 120,
      "2024": 68
    }
  },
  "n_grid": 2688,
  "top_20": [
    {
      "shrink": 0.4,
      "wlin": 0.7,
      "sint": 3.0,
      "sslo": 0.01,
      "per_year_acc": {
        "2010": 1.0,
        "2016": 0.85,
        "2018": 0.9857,
        "2020": 1.0,
        "2022": 1.0,
        "2024": 0.8971
      },
      "avg_acc": 0.9721,
      "avg_brier": 0.1048
    },
    {
      "shrink": 0.35,
      "wlin": 0.7,
      "sint": 3.0,
      "sslo": 0.05,
      "per_year_acc": {
        "2010": 1.0,
        "2016": 0.85,
        "2018": 0.9714,
        "2020": 1.0,
        "2022": 1.0,
        "2024": 0.8971
      },
      "avg_acc": 0.9695,
      "avg_brier": 0.1065
    },
    {
      "shrink": 0.35,
      "wlin": 0.7,
      "sint": 3.0,
      "sslo": 0.06,
      "per_year_acc": {
        "2010": 1.0,
        "2016": 0.85,
        "2018": 0.9714,
        "2020": 1.0,
        "2022": 1.0,
        "2024": 0.8971
      },
      "avg_acc": 0.9695,
      "avg_brier": 0.1071
    },
    {
      "shrink": 0.35,
      "wlin": 0.7,
      "sint": 3.0,
      "sslo": 0.08,
      "per_year_acc": {
        "2010": 1.0,
        "2016": 0.85,
        "2018": 0.9714,
        "2020": 1.0,
        "2022": 1.0,
        "2024": 0.8971
      },
      "avg_acc": 0.9695,
      "avg_brier": 0.1082
    },
    {
      "shrink": 0.4,
      "wlin": 0.7,
      "sint": 3.0,
      "sslo": 0.02,
      "per_year_acc": {
        "2010": 1.0,
        "2016": 0.85,
        "2018": 0.9714,
        "2020": 1.0,
        "2022": 1.0,
        "2024": 0.8971
      },
      "avg_acc": 0.9695,
      "avg_brier": 0.1053
    },
    {
      "shrink": 0.4,
      "wlin": 0.7,
      "sint": 3.0,
      "sslo": 0.03,
      "per_year_acc": {
        "2010": 1.0,
        "2016": 0.85,
        "2018": 0.9714,
        "2020": 1.0,
        "2022": 1.0,
        "2024": 0.8971
      },
      "avg_acc": 0.9695,
      "avg_brier": 0.1059
    },
    {
      "shrink": 0.4,
      "wlin": 0.7,
      "sint": 3.0,
      "sslo": 0.04,
      "per_year_acc": {
        "2010": 1.0,
        "2016": 0.85,
        "2018": 0.9714,
        "2020": 1.0,
        "2022": 1.0,
        "2024": 0.8971
      },
      "avg_acc": 0.9695,
      "avg_brier": 0.1064
    },
    {
      "shrink": 0.4,
      "wlin": 0.7,
      "sint": 3.0,
      "sslo": 0.05,
      "per_year_acc": {
        "2010": 1.0,
        "2016": 0.85,
        "2018": 0.9714,
        "2020": 1.0,
        "2022": 1.0,
        "2024": 0.8971
      },
      "avg_acc": 0.9695,
      "avg_brier": 0.1069
    },
    {
      "shrink": 0.4,
      "wlin": 0.7,
      "sint": 3.0,
      "sslo": 0.06,
      "per_year_acc": {
        "2010": 1.0,
        "2016": 0.85,
        "2018": 0.9714,
        "2020": 1.0,
        "2022": 1.0,
        "2024": 0.8971
      },
      "avg_acc": 0.9695,
      "avg_brier": 0.1075
    },
    {
      "shrink": 0.4,
      "wlin": 0.7,
      "sint": 3.0,
      "sslo": 0.08,
      "per_year_acc": {
        "2010": 1.0,
        "2016": 0.85,
        "2018": 0.9714,
        "2020": 1.0,
        "2022": 1.0,
        "2024": 0.8971
      },
      "avg_acc": 0.9695,
      "avg_brier": 0.1086
    },
    {
      "shrink": 0.05,
      "wlin": 0.7,
      "sint": 3.0,
      "sslo": 0.01,
      "per_year_acc": {
        "2010": 1.0,
        "2016": 0.85,
        "2018": 0.9857,
        "2020": 1.0,
        "2022": 1.0,
        "2024": 0.8676
      },
      "avg_acc": 0.967,
      "avg_brier": 0.1026
    },
    {
      "shrink": 0.05,
      "wlin": 0.7,
      "sint": 3.0,
      "sslo": 0.02,
      "per_year_acc": {
        "2010": 1.0,
        "2016": 0.85,
        "2018": 0.9857,
        "2020": 1.0,
        "2022": 1.0,
        "2024": 0.8676
      },
      "avg_acc": 0.967,
      "avg_brier": 0.103
    },
    {
      "shrink": 0.05,
      "wlin": 0.8,
      "sint": 4.0,
      "sslo": 0.05,
      "per_year_acc": {
        "2010": 1.0,
        "2016": 0.8,
        "2018": 0.9714,
        "2020": 1.0,
        "2022": 1.0,
        "2024": 0.8971
      },
      "avg_acc": 0.967,
      "avg_brier": 0.0963
    },
    {
      "shrink": 0.05,
      "wlin": 0.8,
      "sint": 4.0,
      "sslo": 0.08,
      "per_year_acc": {
        "2010": 1.0,
        "2016": 0.85,
        "2018": 0.9571,
        "2020": 1.0,
        "2022": 1.0,
        "2024": 0.8971
      },
      "avg_acc": 0.967,
      "avg_brier": 0.0981
    },
    {
      "shrink": 0.05,
      "wlin": 0.85,
      "sint": 5.0,
      "sslo": 0.08,
      "per_year_acc": {
        "2010": 1.0,
        "2016": 0.8,
        "2018": 0.9571,
        "2020": 1.0,
        "2022": 1.0,
        "2024": 0.9118
      },
      "avg_acc": 0.967,
      "avg_brier": 0.0968
    },
    {
      "shrink": 0.1,
      "wlin": 0.7,
      "sint": 3.0,
      "sslo": 0.01,
      "per_year_acc": {
        "2010": 1.0,
        "2016": 0.85,
        "2018": 0.9857,
        "2020": 1.0,
        "2022": 1.0,
        "2024": 0.8676
      },
      "avg_acc": 0.967,
      "avg_brier": 0.1028
    },
    {
      "shrink": 0.15,
      "wlin": 0.7,
      "sint": 3.0,
      "sslo": 0.01,
      "per_year_acc": {
        "2010": 1.0,
        "2016": 0.85,
        "2018": 0.9857,
        "2020": 1.0,
        "2022": 1.0,
        "2024": 0.8676
      },
      "avg_acc": 0.967,
      "avg_brier": 0.1031
    },
    {
      "shrink": 0.2,
      "wlin": 0.7,
      "sint": 3.0,
      "sslo": 0.01,
      "per_year_acc": {
        "2010": 1.0,
        "2016": 0.85,
        "2018": 0.9857,
        "2020": 1.0,
        "2022": 1.0,
        "2024": 0.8676
      },
      "avg_acc": 0.967,
      "avg_brier": 0.1035
    },
    {
      "shrink": 0.25,
      "wlin": 0.7,
      "sint": 3.0,
      "sslo": 0.01,
      "per_year_acc": {
        "2010": 1.0,
        "2016": 0.85,
        "2018": 0.9857,
        "2020": 1.0,
        "2022": 1.0,
        "2024": 0.8676
      },
      "avg_acc": 0.967,
      "avg_brier": 0.1038
    },
    {
      "shrink": 0.3,
      "wlin": 0.7,
      "sint": 3.0,
      "sslo": 0.01,
      "per_year_acc": {
        "2010": 1.0,
        "2016": 0.85,
        "2018": 0.9857,
        "2020": 1.0,
        "2022": 1.0,
        "2024": 0.8676
      },
      "avg_acc": 0.967,
      "avg_brier": 0.1041
    }
  ]
}